mancer/__init__.py
mancer/application/__init__.py
mancer/application/command_cache.py
mancer/application/command_library.py
mancer/application/command_manager.py
mancer/application/shell_runner.py
mancer/application/commands/__init__.py
mancer/application/commands/apt_command.py
mancer/application/commands/base_command.py
mancer/application/commands/systemctl_command.py
mancer/application/remote_config_manager/__init__.py
mancer/application/remote_config_manager/__main__.py
mancer/application/remote_config_manager/cli.py
mancer/application/remote_config_manager/config.py
mancer/application/remote_config_manager/file_operations.py
mancer/application/remote_config_manager/manager.py
mancer/application/service/__init__.py
mancer/application/service/remote_config_manager.py
mancer/application/service/systemd_inspector.py
mancer/application/systemd_inspector/__init__.py
mancer/application/systemd_inspector/__main__.py
mancer/application/systemd_inspector/cli.py
mancer/application/systemd_inspector/inspector.py
mancer/domain/__init__.py
mancer/domain/interface/__init__.py
mancer/domain/interface/backend_interface.py
mancer/domain/interface/command_interface.py
mancer/domain/model/__init__.py
mancer/domain/model/command_context.py
mancer/domain/model/command_result.py
mancer/domain/model/config_manager.py
mancer/domain/model/data_format.py
mancer/domain/model/data_structures.py
mancer/domain/model/execution_history.py
mancer/domain/model/execution_step.py
mancer/domain/model/tool_version.py
mancer/domain/model/version_info.py
mancer/domain/service/__init__.py
mancer/domain/service/command_chain_service.py
mancer/domain/service/command_logger_service.py
mancer/domain/service/data_converter_service.py
mancer/domain/service/log_backend_interface.py
mancer/domain/service/systemd_service.py
mancer/domain/service/tool_version_service.py
mancer/domain/shared/__init__.py
mancer/domain/shared/config_balancer.py
mancer/domain/shared/profile_producer.py
mancer-0.1.4.dist-info/licenses/LICENSE
mancer-0.1.4.dist-info/METADATA
mancer-0.1.4.dist-info/WHEEL
mancer-0.1.4.dist-info/top_level.txt
mancer-0.1.4.dist-info/RECORD
