Metadata-Version: 2.4
Name: mancer
Version: 0.1.4
Summary: Framework DDD dla komend systemowych
Author: Kacper Paczos
Author-email: Kacper Paczos <kacperpaczos2024@proton.me>
License: MIT
Keywords: ddd,commands,framework,system
Classifier: Programming Language :: Python :: 3
Classifier: Programming Language :: Python :: 3 :: Only
Classifier: License :: OSI Approved :: MIT License
Classifier: Operating System :: OS Independent
Requires-Python: >=3.8
License-File: LICENSE
Requires-Dist: pandas>=1.5.0
Requires-Dist: numpy>=1.22.0
Requires-Dist: python-dateutil>=2.8.2
Requires-Dist: jsonschema>=4.17.0
Requires-Dist: pyyaml>=6.0
Requires-Dist: icecream>=2.1.3
Requires-Dist: cryptography>=40.0.0
Requires-Dist: configparser>=5.3.0
Requires-Dist: flask>=2.0.0
Provides-Extra: test
Requires-Dist: pytest>=7.0.0; extra == "test"
Provides-Extra: dev
Requires-Dist: ruff>=0.4.0; extra == "dev"
Requires-Dist: black>=24.3.0; extra == "dev"
Requires-Dist: isort>=5.13.0; extra == "dev"
Requires-Dist: mypy>=1.6.0; extra == "dev"
Requires-Dist: pre-commit>=3.6.0; extra == "dev"
Dynamic: author
Dynamic: license-file
Dynamic: requires-python
